{"users": [
{
  "localId": "3o61oOyPu1dlHYpbI1GDCNPJtKx1",
  "email": "user1@test.com",
  "emailVerified": false,
  "passwordHash": "0Z0dNhURKp+P8Tfh4wwIqFiblEjhbYxoFSP3FY0D+aM76ZV3p4VTKB+N2K+zlDGFTlYdhUgCN3bpAQFpSszrJQ==",
  "salt": "sxHY3+JLG6ibHA==",
  "lastSignedInAt": "1744361679404",
  "createdAt": "1744111075894",
  "providerUserInfo": []
},
{
  "localId": "Ht0nEH6Yw0VEtXcRWgYGsakjY6B2",
  "email": "mover3@test.com",
  "emailVerified": false,
  "passwordHash": "k0UEOsT6XnvwbiPkH0xXbZPE7gaWAPI5qj6niisqOmvlHYWPAYk87A+fjg5WDHlSvDcOBIC4PlytwF/l/96r2Q==",
  "salt": "edplD3HQKobSGg==",
  "lastSignedInAt": "1746524986932",
  "createdAt": "1744282166481",
  "providerUserInfo": []
},
{
  "localId": "MIibaCaW1be0gnsaHprL9AwHHhL2",
  "email": "owner1@test.com",
  "emailVerified": false,
  "passwordHash": "JBUnb8d50pYGC1JANWizRo8pqNa5rLQaOshW/Z20cTWvXeOI2m8HYUNQs2bduGKdGRH0eVNVCFXNhc/qROahFQ==",
  "salt": "bs4HdLWRKnTdjw==",
  "lastSignedInAt": "1746528718381",
  "createdAt": "1746526360372",
  "customAttributes": "{\"role\": \"hunter\"}",
  "providerUserInfo": []
},
{
  "localId": "QetgBgRRjVZLZze3SbwfCRoyM6u2",
  "email": "user2@test.com",
  "emailVerified": false,
  "passwordHash": "ncc/nD+aItg0HxPzKAWOsgY4X+ejI8UrWjTtHm68PJ7jYTcAhawSGGxS9NPsmpb02NtzXSARtYotGvZuyUEU2g==",
  "salt": "wt3SJ/Jyp4DThQ==",
  "lastSignedInAt": "1744112178973",
  "createdAt": "1744112178973",
  "providerUserInfo": []
},
{
  "localId": "SWlAwe1oiBP0MT9Pq7c2N9Akm8o2",
  "email": "user@test.com",
  "emailVerified": false,
  "passwordHash": "WXNzsxgGFFcRbvQ5JKWXjfMHaUHh1Cfg3OCwKxhEMbTEx55hBFe6uOTjuT0x7ybODBe2VlrHD5iAmYbAeu+EbA==",
  "salt": "nvwS9Au/vEB+fg==",
  "lastSignedInAt": "1746528804368",
  "createdAt": "1744110471335",
  "providerUserInfo": []
},
{
  "localId": "UaOG5QCweTQvJQxSrDf6G8moDEN2",
  "email": "mikemoves@test.com",
  "emailVerified": false,
  "passwordHash": "5/AJRtMkjPkJt1/E6uACVr6zD47cYPnO4vBCGQs/NIWOv5xRJp7b3BXYdAd0xnvFtCTI4N64vEi0AatDkRh5Tg==",
  "salt": "T89ooxoxXbCHcQ==",
  "lastSignedInAt": "1746690230415",
  "createdAt": "1746690230415",
  "customAttributes": "{\"role\": \"hunter\"}",
  "providerUserInfo": []
},
{
  "localId": "ZFWAhp5FMPVNOPcbrykgzExNOah2",
  "email": "mover@test.com",
  "emailVerified": false,
  "passwordHash": "Wym5Ubd6+SxPD9LJPAIMo1mB64Z651j/7736V/enqVYW40MUPH4pDFQoziJcT/Yfb4qG/z/UsraOLUpdmvZAnA==",
  "salt": "+JXe/bwo6usrkw==",
  "lastSignedInAt": "1744362410469",
  "createdAt": "1744362410469",
  "providerUserInfo": []
},
{
  "localId": "epPvydF2VyM1rPls9kESC5ZZFU82",
  "email": "ltmovers@test.com",
  "emailVerified": false,
  "passwordHash": "mO+FghM+YFPyLnJQhnbz9j7H9l2bASB45ye0tctSu+3nPTa5dVwZBbT+/T7ciUyype84IQcwtaRLMwxakSEYXQ==",
  "salt": "z9oe9Lir9RdYVw==",
  "lastSignedInAt": "1744625924719",
  "createdAt": "1744625924719",
  "providerUserInfo": []
},
{
  "localId": "hPJwbRav1WfA0txCAB7glxa6Thx1",
  "email": "mover1@test.com",
  "emailVerified": false,
  "passwordHash": "m4KRZb7AA24Zb5mn8aoZb/WZHnC3aQ65MHZJ6ALq25el33in1DEM0rNa/LFNitlCGY2yLcl/r5hhnqdB+N1a1w==",
  "salt": "wrfARC2sG/nETA==",
  "lastSignedInAt": "1744279270145",
  "createdAt": "1744279270145",
  "providerUserInfo": []
},
{
  "localId": "xI5nWvhGkzYx5h4RcSYNU3T8MMz2",
  "email": "mover4@test.com",
  "emailVerified": false,
  "passwordHash": "nsJOtiibVd93xcwAQXxvcOTrepG/998ooBj3wgIZ4WqkN6cMHOuAo6uTaN5ZgOdTKDJQsMXmbmkibaa+KlGLOw==",
  "salt": "uczdrKlSPBzjFQ==",
  "lastSignedInAt": "1746523881282",
  "createdAt": "1744283592986",
  "providerUserInfo": []
}]}